Metadata-Version: 2.1
Name: python-speck
Version: 0.0.1
Summary: Speck - Unified observability platform for production LLM apps
Home-page: https://github.com/speckai/speck
Download-URL: https://github.com/speckai/speck/archive/refs/tags/v0.0.1.tar.gz
Author: Lucas Jaggernauth
Author-email: luke@speck.chat
Keywords: speck,openai,llm,ai,chat,bot,gpt,gpt-3
Classifier: Programming Language :: Python :: 3.12
License-File: LICENSE.txt
